enaml/__init__.py
enaml/application.py
enaml/callableref.cp313-win_amd64.pyd
enaml/colorext.cp313-win_amd64.pyd
enaml/colors.py
enaml/compat.py
enaml/compile_all.py
enaml/drag_drop.py
enaml/fontext.cp313-win_amd64.pyd
enaml/fonts.py
enaml/icon.py
enaml/image.py
enaml/mime_data.py
enaml/nodevisitor.py
enaml/objectdict.py
enaml/runner.py
enaml/signaling.cp313-win_amd64.pyd
enaml/styling.py
enaml/validator.py
enaml/version.py
enaml/weakmethod.cp313-win_amd64.pyd
enaml/winutil.cp313-win_amd64.pyd
enaml/applib/__init__.py
enaml/applib/live_editor_model.py
enaml/applib/live_editor_view.enaml
enaml/core/__init__.py
enaml/core/_dynamicscope.cp313-win_amd64.pyd
enaml/core/alias.cp313-win_amd64.pyd
enaml/core/api.py
enaml/core/block_compiler.py
enaml/core/code_generator.py
enaml/core/code_tracing.py
enaml/core/compiler_common.py
enaml/core/compiler_helpers.py
enaml/core/compiler_nodes.py
enaml/core/conditional.py
enaml/core/declarative.py
enaml/core/declarative_function.cp313-win_amd64.pyd
enaml/core/declarative_meta.py
enaml/core/dynamic_template.py
enaml/core/dynamicscope.py
enaml/core/enaml_ast.py
enaml/core/enaml_compiler.py
enaml/core/enamldef_compiler.py
enaml/core/enamldef_meta.py
enaml/core/expression_engine.py
enaml/core/funchelper.cp313-win_amd64.pyd
enaml/core/import_hooks.py
enaml/core/include.py
enaml/core/looper.py
enaml/core/object.py
enaml/core/operators.py
enaml/core/pattern.py
enaml/core/standard_handlers.py
enaml/core/standard_inverter.py
enaml/core/standard_tracer.py
enaml/core/subscription_observer.cp313-win_amd64.pyd
enaml/core/template.py
enaml/core/template_.py
enaml/core/template_compiler.py
enaml/core/parser/__init__.py
enaml/core/parser/base_enaml_parser.py
enaml/core/parser/base_python_parser.py
enaml/core/parser/enaml.gram
enaml/core/parser/enaml_parser.py
enaml/core/parser/generate_enaml_parser.py
enaml/layout/__init__.py
enaml/layout/api.py
enaml/layout/box_helper.py
enaml/layout/constrainable.py
enaml/layout/constraint_helper.py
enaml-0.19.0.dist-info/licenses/LICENSE
enaml-0.19.0.dist-info/METADATA
enaml-0.19.0.dist-info/WHEEL
enaml-0.19.0.dist-info/entry_points.txt
enaml-0.19.0.dist-info/top_level.txt
enaml-0.19.0.dist-info/RECORD
