Metadata-Version: 2.4
Name: enaml
Version: 0.19.0
Summary: Declarative DSL for building rich user interfaces in Python
Author-email: The Nucleic Development Team <sccolbert@gmail.com>
Maintainer-email: "Matthieu C. Dartiailh" <m.dartiailh@gmail.com>
License-Expression: BSD-3-Clause
Project-URL: homepage, https://github.com/nucleic/enaml
Project-URL: documentation, https://enaml.readthedocs.io/en/latest/
Project-URL: repository, https://github.com/nucleic/enaml
Project-URL: changelog, https://github.com/nucleic/enaml/blob/main/releasenotes.rst
Classifier: Programming Language :: Python
Classifier: Programming Language :: Python :: 3
Classifier: Programming Language :: Python :: 3.10
Classifier: Programming Language :: Python :: 3.11
Classifier: Programming Language :: Python :: 3.12
Classifier: Programming Language :: Python :: 3.13
Classifier: Programming Language :: Python :: 3.14
Classifier: Programming Language :: Python :: Implementation :: CPython
Requires-Python: !=3.11.0,!=3.11.1,>=3.10
License-File: LICENSE
Requires-Dist: atom>=0.9.0
Requires-Dist: kiwisolver>=1.2.0
Requires-Dist: bytecode>=0.17.0
Requires-Dist: pegen>=0.3.0
Provides-Extra: qt5-pyqt
Requires-Dist: qtpy>=2.1.0; extra == "qt5-pyqt"
Requires-Dist: PyQt5; extra == "qt5-pyqt"
Provides-Extra: qt5-pyside
Requires-Dist: qtpy>=2.1.0; extra == "qt5-pyside"
Requires-Dist: pyside2; extra == "qt5-pyside"
Provides-Extra: qt6-pyqt
Requires-Dist: qtpy>=2.1.0; extra == "qt6-pyqt"
Requires-Dist: PyQt6>=6.3.1; extra == "qt6-pyqt"
Provides-Extra: qt6-pyside
Requires-Dist: qtpy>=2.3.0; extra == "qt6-pyside"
Requires-Dist: pyside6>=6.2.3; extra == "qt6-pyside"
Provides-Extra: scintilla-qt5-pyqt
Requires-Dist: QScintilla; extra == "scintilla-qt5-pyqt"
Provides-Extra: scintilla-qt6-pyqt
Requires-Dist: PyQt6-QScintilla; extra == "scintilla-qt6-pyqt"
Provides-Extra: matplotlib-qt
Requires-Dist: matplotlib; extra == "matplotlib-qt"
Provides-Extra: ipython-qt
Requires-Dist: qtconsole; extra == "ipython-qt"
Provides-Extra: webview-qt5-pyqt
Requires-Dist: PyQtWebEngine; extra == "webview-qt5-pyqt"
Provides-Extra: webview-qt6-pyqt
Requires-Dist: PyQt6-WebEngine; extra == "webview-qt6-pyqt"
Provides-Extra: vtk-qt
Requires-Dist: vtk; extra == "vtk-qt"
Dynamic: license-file
